[{"title":"v1.6.0","link":"https://github.com/scrtlabs/SecretNetwork/releases/tag/v1.6.0","pubDate":"2022-12-12T08:53:26.000Z","author":"github-actions[bot]","content":"<p>Merge pull request <a class=\"issue-link js-issue-link\" href=\"https://github.com/scrtlabs/SecretNetwork/pull/1284\">#1284</a> from scrtlabs/fix-oom-cache</p>\n\n<p>Fix writable gas tracking</p>","contentSnippet":"Merge pull request #1284 from scrtlabs/fix-oom-cache\nFix writable gas tracking","id":"tag:github.com,2008:Repository/236962590/v1.6.0","isoDate":"2022-12-12T08:53:26.000Z"},{"creator":"luc:","title":"穩定幣觀測》USDC 在以太坊上轉移量月佔比超 60%，遠超USDT、BUSD","link":"https://www.blocktempo.com/usdc-transfer-volume-lasy-30-days-was-over-60-percents/","pubDate":"Mon, 12 Dec 2022 08:55:54 +0000","dc:creator":"luc:","comments":"https://www.blocktempo.com/usdc-transfer-volume-lasy-30-days-was-over-60-percents/#respond","content":"<p>數據指出在以太坊上穩定幣轉移量佔比，USDC 當前超過 60% 穩居第一、供應量也排名第一。此前 Coinba [&#8230;]</p>\n〈<a href=\"https://www.blocktempo.com/usdc-transfer-volume-lasy-30-days-was-over-60-percents/\">穩定幣觀測》USDC 在以太坊上轉移量月佔比超 60%，遠超USDT、BUSD</a>〉這篇文章最早發佈於動區BlockTempo《<a href=\"https://www.blocktempo.com\">動區動趨-最具影響力的區塊鏈媒體 (比特幣, 加密貨幣)</a>》。","contentSnippet":"數據指出在以太坊上穩定幣轉移量佔比，USDC 當前超過 60% 穩居第一、供應量也排名第一。此前 Coinba […]\n穩定幣觀測》USDC 在以太坊上轉移量月佔比超 60%，遠超USDT、BUSD〉這篇文章最早發佈於動區BlockTempo《動區動趨-最具影響力的區塊鏈媒體 (比特幣, 加密貨幣)》。","guid":"https://www.blocktempo.com/?p=200700","categories":["加密貨幣市場","即時新聞","穩定幣","BUSD","USDC","USDT"],"isoDate":"2022-12-12T08:55:54.000Z"}]